LICENSE
README.md
pyproject.toml
setup.cfg
src/ravf/__init__.py
src/ravf/metadata_entry.py
src/ravf/ravf_frame.py
src/ravf/ravf_header.py
src/ravf/ravf_image_utils.py
src/ravf/ravf_index.py
src/ravf/ravf_reader.py
src/ravf/ravf_writer.py
src/ravf.egg-info/PKG-INFO
src/ravf.egg-info/SOURCES.txt
src/ravf.egg-info/dependency_links.txt
src/ravf.egg-info/requires.txt
src/ravf.egg-info/top_level.txt