Metadata-Version: 2.1
Name: ravf
Version: 1.0.1
Summary: Raw Astro Video Format - File format designed to store raw frames from a camera in realtime primarily for Occultations
Home-page: https://github.com/ChasinSpin/ravf
Author: ChasinSpin
Author-email: 
Project-URL: Bug Tracker, https://github.com/ChasinSpin/ravf/issues
Classifier: Programming Language :: Python :: 3
Classifier: License :: OSI Approved :: MIT License
Classifier: Operating System :: OS Independent
Requires-Python: >=3.7
License-File: LICENSE
